agentcp/__init__.py
agentcp/agent.py
agentcp/agentcp.py
agentcp/ap_client.py
agentcp/auth_client.py
agentcp/ca_client.py
agentcp/ca_root.py
agentcp/client.py
agentcp/entrypoint_client.py
agentcp/env.py
agentcp/group_manager.py
agentcp/heartbeat_client.py
agentcp/html_util.py
agentcp/llm_agent_utils.py
agentcp/llm_server.py
agentcp/log.py
agentcp/mermaid.py
agentcp/message.py
agentcp/message_client.py
agentcp/message_serialize.py
agentcp/open_ai_message.py
agentcp/session_manager.py
agentcp/stream_client.py
agentcp/workflow.py
agentcp/wss_binary_message.py
agentcp/ap/__init__.py
agentcp/ap/ap_client.py
agentcp/base/__init__.py
agentcp/base/auth_client.py
agentcp/base/client.py
agentcp/base/env.py
agentcp/base/html_util.py
agentcp/base/log.py
agentcp/ca/__init__.py
agentcp/ca/ca_client.py
agentcp/ca/ca_root.py
agentcp/context/__init__.py
agentcp/context/context.py
agentcp/context/exceptions.py
agentcp/db/__init__.py
agentcp/db/db_mananger.py
agentcp/file/__init__.py
agentcp/file/file_client.py
agentcp/file/wss_binary_message.py
agentcp/heartbeat/__init__.py
agentcp/heartbeat/heartbeat_client.py
agentcp/msg/__init__.py
agentcp/msg/message_client.py
agentcp/msg/message_serialize.py
agentcp/msg/open_ai_message.py
agentcp/msg/session_manager.py
agentcp/msg/stream_client.py
agentcp/msg/websocket_file_receiver.py
agentcp/msg/wss_binary_message.py
agentcp/utils/__init__.py
agentcp/utils/file_util.py
agentcp-0.1.99.dist-info/licenses/LICENCE
agentcp-0.1.99.dist-info/METADATA
agentcp-0.1.99.dist-info/WHEEL
agentcp-0.1.99.dist-info/top_level.txt
agentcp-0.1.99.dist-info/RECORD
