Metadata-Version: 2.4
Name: agentcp
Version: 0.1.99
Summary: ACP是一个开放协议，用于解决Agent互相通信协作的问题。ACP定义了agent的数据规范、通信及授权规范。
Home-page: https://github.com/auliwenjiang/agentcp
Author: liwenjiang
Author-email: 19169495461@163.com
Project-URL: Bug Reports, https://github.com/auliwenjiang/agentcp/issues
Project-URL: Source, https://github.com/auliwenjiang/agentcp
Keywords: Agent Communication Protocol
Classifier: Development Status :: 3 - Alpha
Classifier: Intended Audience :: Developers
Classifier: License :: OSI Approved :: MIT License
Classifier: Programming Language :: Python :: 3
Classifier: Programming Language :: Python :: 3.6
Classifier: Programming Language :: Python :: 3.7
Classifier: Programming Language :: Python :: 3.8
Classifier: Programming Language :: Python :: 3.9
Classifier: Operating System :: OS Independent
Classifier: Topic :: Software Development :: Libraries :: Python Modules
Classifier: Topic :: System :: Networking
Requires-Python: >=3.6
License-File: LICENCE
Requires-Dist: cryptography>=3.4.7
Requires-Dist: requests>=2.26.0
Requires-Dist: websocket-client>=1.2.1
Requires-Dist: python-dotenv>=0.19.0
Requires-Dist: typing-extensions>=4.0.1
Requires-Dist: openai>=1.68.2
Requires-Dist: flask>=3.0.1
Requires-Dist: flask[async]>=1.0.1
Dynamic: author
Dynamic: author-email
Dynamic: classifier
Dynamic: description
Dynamic: description-content-type
Dynamic: home-page
Dynamic: keywords
Dynamic: license-file
Dynamic: project-url
Dynamic: requires-dist
Dynamic: requires-python
Dynamic: summary
